detect_gene_feature-0.1.9.dist-info/METADATA
detect_gene_feature-0.1.9.dist-info/WHEEL
detect_gene_feature/__init__.py
detect_gene_feature/detect_gene_feature.cpython-38-x86_64-linux-gnu.so
detect_gene_feature-0.1.9.dist-info/RECORD
